llm_components/__init__.py
llm_components/cli.py
llm_components/version.py
llm_components/loaders/__init__.py
llm_components/loaders/code_base.py
llm_components/loaders/git_utils.py
llm_components/loaders/utils.py
llm_components/loaders/web_to_markdown.py
llm_components-1.3.2.dist-info/LICENSE
llm_components-1.3.2.dist-info/METADATA
llm_components-1.3.2.dist-info/WHEEL
llm_components-1.3.2.dist-info/entry_points.txt
llm_components-1.3.2.dist-info/top_level.txt
llm_components-1.3.2.dist-info/RECORD
