Metadata-Version: 2.1
Name: llm-components
Version: 1.3.2
Summary: A library of ready-to-use LLM components
Home-page: https://github.com/advanced-stack/llm-components
Author: P.A. SCHEMBRI
Author-email: pa.schembri@advanced-stack.com
License: MIT
License-File: LICENSE
Requires-Dist: pathspec
Requires-Dist: beautifulsoup4
Requires-Dist: requests
Requires-Dist: markdownify
